Metadata-Version: 2.1
Name: alvenirclient
Version: 0.0.2
Summary: Client for alvenir gRPC streaming services
Home-page: https://github.com/alvenirai/alvenirclient
Author: Rasmus Arpe Fogh Egebæk
Author-email: rasmus@alvenir.ai
License: UNKNOWN
Platform: UNKNOWN
Classifier: Programming Language :: Python :: 3
Classifier: Development Status :: 5 - Production/Stable
Classifier: Operating System :: OS Independent
